[
    {
        "claim": "the MT system is capable of providing wordis generally true for current statistical MT systems", 
        "claim_score": 0.42581888, 
        "evidence_score": -0.55437614, 
        "text": "We assume here that the MT system is capable of providing word alignment ( or equivalent ) information during decoding , which is generally true for current statistical MT systems ."
    }, 
    {
        "claim": "partial SRSs must be recorded inthey can be combined", 
        "claim_score": 0.25668134, 
        "evidence_score": -0.37637641, 
        "text": "In such cases partial SRSs must be recorded in such a way that they can be combined later with other partial SRSs ."
    }, 
    {
        "claim": "Considering our semantic features are the most basic onesprovides a possible direction for further experimentation", 
        "claim_score": 0.071380318, 
        "evidence_score": -0.13894744, 
        "text": "Considering our semantic features are the most basic ones , using more sophisticated features ( e.g the head words and their translations of the sourceside semantic roles ) provides a possible direction for further experimentation"
    }
]