<?xml version="1.0" encoding="UTF-8"?><document><sentence><claim_score>-0.71397848</claim_score><evidence_score>-0.65575407</evidence_score><text>Abstract Humans and animals learn much better when the examples are not randomly presented but organized in a meaningful order which illustrates gradually more concepts , and gradually more complex ones .</text>
<not_argumentative> Abstract Humans and animals learn much better when the examples are not randomly presented but organized in a meaningful order which illustrates gradually more concepts , and gradually more complex ones .</not_argumentative>
</sentence>
<sentence><claim_score>-0.70949353</claim_score><evidence_score>-0.29160604</evidence_score><text>Here , we formalize such training strategies in the context of machine learning , and call them `` curriculum learning '' .</text>
<not_argumentative> Here , we formalize such training strategies in the context of machine learning , and call them `` curriculum learning '' .</not_argumentative>
</sentence>
<sentence><claim_score>-1.0036083</claim_score><evidence_score>-0.14053428</evidence_score><text>In the context of recent research studying the difficulty of training in the presence of non-convex training criteria ( for deep deterministic and stochastic neural networks ) , we explore curriculum learning in various set-ups .</text>
<not_argumentative> In the context of recent research studying the difficulty of training in the presence of non-convex training criteria ( for deep deterministic and stochastic neural networks ) , we explore curriculum learning in various set-ups .</not_argumentative>
</sentence>
<sentence><claim_score>1.1324365</claim_score><evidence_score>0.32091019</evidence_score><text>The experiments show that significant improvements in generalization can be achieved .</text>
<claim_evidence> significant improvements in generalization can be achieved</claim_evidence>
<evidence> The experiments show that significant improvements in generalization can be achieved .</evidence>
</sentence>
<sentence><claim_score>0.29801851</claim_score><evidence_score>0.030985303</evidence_score><text>We hypothesize that curriculum learning has both an effect on the speed of convergence of the training process to a minimum and , in the case of non-convex criteria , on the quality of the local minima obtained : curriculum learning can be seen as a particular form of continuation method ( a general strategy for global optimization of non-convex functions ) .</text>
<claim_evidence> curriculum learning has both an effect on the speed of convergence of the training process to a minimum</claim_evidence>
<claim_evidence> curriculum learning can be seen as a particular form of continuation method ( a general strategy for global optimization</claim_evidence>
<evidence> We hypothesize that curriculum learning has both an effect on the speed of convergence of the training process to a minimum and , in the case of non-convex criteria , on the quality of the local minima obtained : curriculum learning can be seen as a particular form of continuation method ( a general strategy for global optimization of non-convex functions ) .</evidence>
</sentence>
<sentence><claim_score>-1.1142429</claim_score><evidence_score>0.1669702</evidence_score><text>Discussion and Future Work We started with the following question left from previous cognitive science research ( Elman , 1993 ; Rohde & Plaut , 1999 ) : can machine learning algorithms benefit from a curriculum strategy ?</text>
<evidence> Discussion and Future Work We started with the following question left from previous cognitive science research ( Elman , 1993 ; Rohde & Plaut , 1999 ) : can machine learning algorithms benefit from a curriculum strategy ?</evidence>
</sentence>
<sentence><claim_score>-0.1837163</claim_score><evidence_score>-0.26322226</evidence_score><text>Our experimental results in many different settings bring evidence towards a positive answer to that question .</text>
<not_argumentative> Our experimental results in many different settings bring evidence towards a positive answer to that question .</not_argumentative>
</sentence>
<sentence><claim_score>0.48458135</claim_score><evidence_score>0.42872795</evidence_score><text>It is plausible that some curriculum strategies work better than others , that some are actually useless for some tasks ( as in Rohde and Plaut ( 1999 ) ) , and that better results could be obtained on our data sets with more appropriate curriculum strategies .</text>
<claim_evidence> some curriculum strategies work better than others</claim_evidence>
<claim_evidence> some are actually useless for some tasks</claim_evidence>
<claim_evidence> better results could be obtained on our data sets with more appropriate curriculum strategies</claim_evidence>
<evidence> It is plausible that some curriculum strategies work better than others , that some are actually useless for some tasks ( as in Rohde and Plaut ( 1999 ) ) , and that better results could be obtained on our data sets with more appropriate curriculum strategies .</evidence>
</sentence>
<sentence><claim_score>0.36834645</claim_score><evidence_score>-0.24976453</evidence_score><text>After all , the art of teaching is difficult and humans do not agree among themselves about the order in which concepts should be introduced to pupils .</text>
<claim> the art of teaching is difficult and humans do not agree among themselves about the order in which concepts should be introduced to pupils</claim>
</sentence>
<sentence><claim_score>-0.27772754</claim_score><evidence_score>-0.70454677</evidence_score><text>From the machine learning point of view , once the success of some curriculum strategies has been established , the important questions are : why ?</text>
<not_argumentative> From the machine learning point of view , once the success of some curriculum strategies has been established , the important questions are : why ?</not_argumentative>
</sentence>
<sentence><claim_score>-2.0008585</claim_score><evidence_score>-1.0786159</evidence_score><text>and how ?</text>
<not_argumentative> and how ?</not_argumentative>
</sentence>
<sentence><claim_score>-0.37553485</claim_score><evidence_score>0.27617082</evidence_score><text>This is important to help us devise better curriculum strategies and automate that process to some extent .</text>
<evidence> This is important to help us devise better curriculum strategies and automate that process to some extent .</evidence>
</sentence>
<sentence><claim_score>0.083496892</claim_score><evidence_score>-0.18789014</evidence_score><text>We proposed a number of hypotheses to explain the potential advantages of a curriculum strategy : • faster training in the online setting ( i.e. faster both from an optimization and statistical point of view ) because the learner wastes less time with noisy or harder to predict examples ( when it is not ready to incorporate them ) , • guiding training towards better regions in parameter space , i.e. into basins of attraction ( local minima ) of the descent procedure associated with better generalization : a curriculum can be seen as a particular continuation method .</text>
<claim> learner wastes less time with noisy</claim>
<claim> a curriculum can be seen as a particular continuation method</claim>
</sentence>
<sentence><claim_score>-2.2889526</claim_score><evidence_score>0.0033069227</evidence_score><text>Faster convergence with a curriculum was already observed in ( Krueger & Dayan , 2009 ) .</text>
<evidence> Faster convergence with a curriculum was already observed in ( Krueger & Dayan , 2009 ) .</evidence>
</sentence>
<sentence><claim_score>0.063518368</claim_score><evidence_score>0.35694864</evidence_score><text>However , unlike in our experiments where capacity is fixed throughout the curriculum , they found that compared to using no curriculum , worse results were obtained with fixed neural resources .</text>
<claim_evidence> capacity is fixed throughout the curriculum</claim_evidence>
<claim_evidence> compared to using no curriculum , worse results were obtained with fixed neural resources</claim_evidence>
<evidence> However , unlike in our experiments where capacity is fixed throughout the curriculum , they found that compared to using no curriculum , worse results were obtained with fixed neural resources .</evidence>
</sentence>
<sentence><claim_score>-1.4380957</claim_score><evidence_score>-0.36848993</evidence_score><text>The reasons for these differences remain to be clarified .</text>
<not_argumentative> The reasons for these differences remain to be clarified .</not_argumentative>
</sentence>
<sentence><claim_score>-0.64553162</claim_score><evidence_score>0.14698663</evidence_score><text>In both cases , though , an appropriate curriculum strategy acts to help the training process ( faster convergence to better solutions ) , and we even find that it regularizes , giving rise to lower generalization error for the same training error .</text>
<evidence> In both cases , though , an appropriate curriculum strategy acts to help the training process ( faster convergence to better solutions ) , and we even find that it regularizes , giving rise to lower generalization error for the same training error .</evidence>
</sentence>
<sentence><claim_score>-1.4305711</claim_score><evidence_score>-0.20341403</evidence_score><text>This is like in the case of unsupervised pre-training ( Erhan et al. , 2009 ) , and again it remains to be clarified why one would expect improved generalization , for both curriculum and unsupervised pre-training procedures .</text>
<not_argumentative> This is like in the case of unsupervised pre-training ( Erhan et al. , 2009 ) , and again it remains to be clarified why one would expect improved generalization , for both curriculum and unsupervised pre-training procedures .</not_argumentative>
</sentence>
<sentence><claim_score>-0.33999618</claim_score><evidence_score>-0.28173901</evidence_score><text>The way we have defined curriculum strategies leaves a lot to be defined by the teacher .</text>
<not_argumentative> The way we have defined curriculum strategies leaves a lot to be defined by the teacher .</not_argumentative>
</sentence>
<sentence><claim_score>0.75193361</claim_score><evidence_score>0.54850431</evidence_score><text>It would be nice to understand general principles that make some curriculum strategies work better than others , and this clearly should be the subject of future work on curriculum learning .</text>
<claim_evidence> It would be nice to understand general principles that make some curriculum strategies work better than others</claim_evidence>
<claim_evidence> should be the subject of future work on curriculum learning</claim_evidence>
<evidence> It would be nice to understand general principles that make some curriculum strategies work better than others , and this clearly should be the subject of future work on curriculum learning .</evidence>
</sentence>
<sentence><claim_score>0.016234975</claim_score><evidence_score>-0.3050749</evidence_score><text>In particular , to reap the advantages of a curriculum strategy while minimizing the amount of human ( teacher ) effort involved , it is natural to consider a form of active selection of examples similar to what humans ( and in particular children ) do .</text>
<claim> it is natural to consider a form of active selection of examples similar to what humans</claim>
</sentence>
<sentence><claim_score>-0.45733314</claim_score><evidence_score>-0.72934598</evidence_score><text>At any point during the `` education '' of a learner , some examples can be considered `` too easy '' ( not helping much to improve the current model ) , while some examples can be considered `` too difficult '' ( no small change in the model would allow to capture these examples ) .</text>
<not_argumentative> At any point during the `` education '' of a learner , some examples can be considered `` too easy '' ( not helping much to improve the current model ) , while some examples can be considered `` too difficult '' ( no small change in the model would allow to capture these examples ) .</not_argumentative>
</sentence>
<sentence><claim_score>-0.6921286</claim_score><evidence_score>-0.32427393</evidence_score><text>It would be advantageous for a learner to focus on `` interesting '' examples , which would be standing near the frontier of the learner 's knowledge and abilities , neither too easy nor too hard .</text>
<not_argumentative> It would be advantageous for a learner to focus on `` interesting '' examples , which would be standing near the frontier of the learner 's knowledge and abilities , neither too easy nor too hard .</not_argumentative>
</sentence>
<sentence><claim_score>-0.94028412</claim_score><evidence_score>-0.34340577</evidence_score><text>Such an approach could be used to at least automate the pace at which a learner would move along a predefined curriculum .</text>
<not_argumentative> Such an approach could be used to at least automate the pace at which a learner would move along a predefined curriculum .</not_argumentative>
</sentence>
<sentence><claim_score>-2.2595207</claim_score><evidence_score>0.11779991</evidence_score><text>In the experiments we performed , that pace was fixed arbitrarily .</text>
<evidence> In the experiments we performed , that pace was fixed arbitrarily .</evidence>
</sentence>
<sentence><claim_score>-0.53368495</claim_score><evidence_score>-0.080968499</evidence_score><text>This kind of strategy is clearly connected to active learning ( Cohn et al. , 1995 ) , but with a view that is different from the standard one : instead of focusing on the examples near the decision surface to quickly infer its location , we think of the set of examples that the learner succeeds to capture and gradually expand that set by preferentially adding examples near its border .</text>
<not_argumentative> This kind of strategy is clearly connected to active learning ( Cohn et al. , 1995 ) , but with a view that is different from the standard one : instead of focusing on the examples near the decision surface to quickly infer its location , we think of the set of examples that the learner succeeds to capture and gradually expand that set by preferentially adding examples near its border .</not_argumentative>
</sentence>
<sentence><claim_score>-0.65856388</claim_score><evidence_score>-0.81826803</evidence_score><text>Curriculum learning is related to boosting algorithms , in that difficult examples are gradually emphasized .</text>
<not_argumentative> Curriculum learning is related to boosting algorithms , in that difficult examples are gradually emphasized .</not_argumentative>
</sentence>
<sentence><claim_score>-0.8636326</claim_score><evidence_score>-0.48918173</evidence_score><text>However , a curriculum starts with a focus on the easier examples , rather than a uniform distribution over the training set .</text>
<not_argumentative> However , a curriculum starts with a focus on the easier examples , rather than a uniform distribution over the training set .</not_argumentative>
</sentence>
<sentence><claim_score>-0.0086012131</claim_score><evidence_score>-0.32873617</evidence_score><text>Furthermore , from the point of view of the boosted weighted sum of weak learners , there is no change in the training criterion : the change is only from the point of view of the next weak learner .</text>
<not_argumentative> Furthermore , from the point of view of the boosted weighted sum of weak learners , there is no change in the training criterion : the change is only from the point of view of the next weak learner .</not_argumentative>
</sentence>
<sentence><claim_score>-0.33193401</claim_score><evidence_score>-0.4381796</evidence_score><text>As far as the boosted sum is concerned , we are following a functional gradient on the same training criterion ( the sum of exponentiated margins ) .</text>
<not_argumentative> As far as the boosted sum is concerned , we are following a functional gradient on the same training criterion ( the sum of exponentiated margins ) .</not_argumentative>
</sentence>
<sentence><claim_score>-1.3137821</claim_score><evidence_score>-1.1094588</evidence_score><text>Curriculum strategies are also connected to transfer ( or multi-task ) learning and lifelong learning ( Thrun , 1996 ) .</text>
<not_argumentative> Curriculum strategies are also connected to transfer ( or multi-task ) learning and lifelong learning ( Thrun , 1996 ) .</not_argumentative>
</sentence>
<sentence><claim_score>-0.025065023</claim_score><evidence_score>-0.4820811</evidence_score><text>Curriculum learning strategies can be seen as a special form of transfer learning where the initial tasks are used to guide the learner so that it will perform better on the final task .</text>
<not_argumentative> Curriculum learning strategies can be seen as a special form of transfer learning where the initial tasks are used to guide the learner so that it will perform better on the final task .</not_argumentative>
</sentence>
<sentence><claim_score>0.20327141</claim_score><evidence_score>-0.46151377</evidence_score><text>Whereas the traditional motivation for multitask learning is to improve generalization by sharing across tasks , curriculum learning adds the notion of guiding the optimization process , either to converge faster , or more importantly , to guide the learner towards better local minima .</text>
<claim> the traditional motivation for multitask learning is to improve generalization</claim>
<claim> curriculum learning adds the notion of guiding the optimization process</claim>
<claim> to guide the learner towards better local minima</claim>
</sentence>
<sentence><claim_score>-0.73774404</claim_score><evidence_score>0.29145738</evidence_score><text>Curriculum Learning Acknowledgements : The authors thank NSERC , CIFAR , and MITACS for support .</text>
<evidence> Curriculum Learning Acknowledgements : The authors thank NSERC , CIFAR , and MITACS for support .</evidence>
</sentence>
<sentence><claim_score>-2.3893531</claim_score><evidence_score>-0.85595776</evidence_score><text>References Allgower , E. L.</text>
<not_argumentative> References Allgower , E. L.</not_argumentative>
</sentence>
</document>